ndx_fiber_photometry/spec/ndx-fiber-photometry.extensions.yaml
ndx_fiber_photometry/spec/ndx-fiber-photometry.namespace.yaml
ndx_fiber_photometry/__init__.py
ndx_fiber_photometry/fiber_photometry.py
ndx_fiber_photometry-0.2.3.dist-info/METADATA
ndx_fiber_photometry-0.2.3.dist-info/WHEEL
ndx_fiber_photometry-0.2.3.dist-info/licenses/LICENSE.txt
ndx_fiber_photometry-0.2.3.dist-info/RECORD
