Metadata-Version: 2.4
Name: ndx-fiber-photometry
Version: 0.2.3
Summary: This is an NWB extension for storing fiber photometry recordings and associated metadata.
Project-URL: Homepage, https://github.com/organization/ndx-fiber-photometry
Project-URL: Bug Tracker, https://github.com/organization/ndx-fiber-photometry/issues
Author-email: Alessandra Trapani <alessandra.trapani@catalystneuro.com>, Luiz Tauffer <luiz.tauffer@catalystneuro.com>, Paul Adkisson <paul.adkisson@catalystneuro.com>, Szonja Weigl <szonja.weigl@catalystneuro.com>
License: BSD-3
License-File: LICENSE.txt
Keywords: NWB,NeurodataWithoutBorders,ndx-extension,nwb-extension
Classifier: Intended Audience :: Developers
Classifier: Intended Audience :: Science/Research
Classifier: License :: OSI Approved :: BSD License
Classifier: Programming Language :: Python :: 3.8
Classifier: Programming Language :: Python :: 3.9
Classifier: Programming Language :: Python :: 3.10
Classifier: Programming Language :: Python :: 3.11
Classifier: Programming Language :: Python :: 3.12
Requires-Dist: hdmf>=4.1.0
Requires-Dist: ndx-ophys-devices>=0.3.1
Requires-Dist: pynwb>=3.1.0
